{"InfoPerso":{"age":"18","enfant":0,"job":"etudiant","langues":{"Allemand":false,"Anglais":true,"Arabe":false,"Espagnol":false,"Français":false,"Japonais":true,"Portugais":true,"chinois":false},"nivEtude":"college","salaire":500,"sexe":"Homme","statut":"fiance"},"ModeVie":{"compagnie":[],"typeHebergement":[],"typeVoyages":[]},"__v":0,"_id":{"$oid":"5587e16b5fa0c34c094b41fe"},"annoncesVideo":[],"email":"admin@admin","name":"admin","password":"$2a$10$6V0p0hgfk0BwUf6tPUmLf.AoFT6Eje/FccypDSiA8KZ80xgEUtHJe","portefeuille":5}
{"InfoPerso":{"langues":[]},"ModeVie":{"compagnie":[],"typeHebergement":[],"typeVoyages":[]},"__v":0,"_id":{"$oid":"558bced1885108101eb86cd3"},"annonces":[{"lien":"http://tn.audi.com/tn/brand/fr.html","url":"images/audi.png"}],"annoncesVideo":[],"annoncesVideos":[],"email":"yo@yo","name":"yoyo","password":"$2a$10$.NBy8qufIUs69R6R5zHS6OIK5rVh7FdKJevSdWgC0P41PZpZRQBD2","portefeuille":15}
{"InfoPerso":{"langues":[]},"ModeVie":{"compagnie":[],"typeHebergement":[],"typeVoyages":[]},"__v":0,"_id":{"$oid":"55969c8e57f85b58113fbf76"},"annonces":[{"lien":"https://www.asus.com/fr/","url":"images/asus.png"},{"lien":"https://www.mcdonalds.fr/produits/sandwichs/big-mac","url":"images/bigmac.png"},{"lien":"http://iphone7-s.fr/","url":"images/iphone.png"},{"lien":"https://play.google.com/store/apps/details?id=com.facebook.katana\u0026hl=fr","url":"images/facebook.png"},{"lien":"http://euw.leagueoflegends.com/fr","url":"images/lol.png"},{"lien":"http://tn.audi.com/tn/brand/fr.html","url":"images/audi.png"}],"annoncesVideos":[{"check":false,"url":"https://www.youtube.com/watch/oYOKp9j-_yY"},{"check":false,"url":"https://www.youtube.com/watch/lC1pBoxvpzw"},{"check":false,"url":"https://www.youtube.com/watch/15R7I5cH6QA"},{"check":false,"url":"https://www.youtube.com/watch/R4-YdC5N6Lo"},{"check":false,"url":"https://www.youtube.com/watch/6AytbSdWBKg"},{"check":false,"url":"https://www.youtube.com/watch/DfW5OLBibmk"}],"email":"walid@walid","name":"walid","password":"$2a$10$dMURJTJwoWZfxnwCBc4ZN.HFHQeK2fPUZ1g5QuiYO4kSPQxZKBduy","portefeuille":117}
